odoo/addons/fieldservice_equipment_stock/README.rst
odoo/addons/fieldservice_equipment_stock/__init__.py
odoo/addons/fieldservice_equipment_stock/__manifest__.py
odoo/addons/fieldservice_equipment_stock/i18n/fieldservice_equipment_stock.pot
odoo/addons/fieldservice_equipment_stock/migrations/12.0.1.0.0/post-migration.py
odoo/addons/fieldservice_equipment_stock/models/__init__.py
odoo/addons/fieldservice_equipment_stock/models/fsm_equipment.py
odoo/addons/fieldservice_equipment_stock/models/product_template.py
odoo/addons/fieldservice_equipment_stock/models/stock_move.py
odoo/addons/fieldservice_equipment_stock/models/stock_picking_type.py
odoo/addons/fieldservice_equipment_stock/models/stock_production_lot.py
odoo/addons/fieldservice_equipment_stock/readme/CONFIGURE.rst
odoo/addons/fieldservice_equipment_stock/readme/CONTRIBUTORS.rst
odoo/addons/fieldservice_equipment_stock/readme/CREDITS.rst
odoo/addons/fieldservice_equipment_stock/readme/DESCRIPTION.rst
odoo/addons/fieldservice_equipment_stock/readme/ROADMAP.rst
odoo/addons/fieldservice_equipment_stock/readme/USAGE.rst
odoo/addons/fieldservice_equipment_stock/security/ir.model.access.csv
odoo/addons/fieldservice_equipment_stock/static/description/icon.png
odoo/addons/fieldservice_equipment_stock/static/description/index.html
odoo/addons/fieldservice_equipment_stock/tests/__init__.py
odoo/addons/fieldservice_equipment_stock/tests/test_fsm_equipment.py
odoo/addons/fieldservice_equipment_stock/views/fsm_equipment.xml
odoo/addons/fieldservice_equipment_stock/views/product_template.xml
odoo/addons/fieldservice_equipment_stock/views/stock_picking_type.xml
odoo/addons/fieldservice_equipment_stock/views/stock_production_lot.xml
odoo12_addon_fieldservice_equipment_stock-12.0.2.0.0.dist-info/METADATA
odoo12_addon_fieldservice_equipment_stock-12.0.2.0.0.dist-info/WHEEL
odoo12_addon_fieldservice_equipment_stock-12.0.2.0.0.dist-info/top_level.txt
odoo12_addon_fieldservice_equipment_stock-12.0.2.0.0.dist-info/RECORD
